llm_stack_watch/__init__.py
llm_stack_watch/config/__init__.py
llm_stack_watch/config/settings.py
llm_stack_watch/core/__init__.py
llm_stack_watch/core/base.py
llm_stack_watch/core/logger.py
llm_stack_watch/core/trace.py
llm_stack_watch/providers/__init__.py
llm_stack_watch/providers/anthropic.py
llm_stack_watch/providers/base.py
llm_stack_watch/providers/google.py
llm_stack_watch/providers/openai.py
llm_stack_watch/tests/__init__.py
llm_stack_watch/tests/conftest.py
llm_stack_watch/tests/test_config.py
llm_stack_watch/utils/__init__.py
llm_stack_watch/utils/exceptions.py
llm_stack_watch/utils/helpers.py
llm_stack_watch-0.1.7.dist-info/licenses/LICENSE
llm_stack_watch-0.1.7.dist-info/METADATA
llm_stack_watch-0.1.7.dist-info/WHEEL
llm_stack_watch-0.1.7.dist-info/top_level.txt
llm_stack_watch-0.1.7.dist-info/RECORD
